beakerx_kernel_autotranslation/__init__.py
beakerx_kernel_autotranslation/_version.py
beakerx_kernel_autotranslation/beakerx_autotranslation_server.py
beakerx_kernel_autotranslation/commands.py
beakerx_kernel_autotranslation/install.py
beakerx_kernel_autotranslation/jvm_kernel_magic.py
beakerx_kernel_autotranslation/jvm_server.py
beakerx_kernel_autotranslation/__pycache__/__init__.cpython-37.pyc
beakerx_kernel_autotranslation/__pycache__/_version.cpython-37.pyc
beakerx_kernel_autotranslation/__pycache__/beakerx_autotranslation_server.cpython-37.pyc
beakerx_kernel_autotranslation/__pycache__/commands.cpython-37.pyc
beakerx_kernel_autotranslation/__pycache__/install.cpython-37.pyc
beakerx_kernel_autotranslation/__pycache__/jvm_kernel_magic.cpython-37.pyc
beakerx_kernel_autotranslation/__pycache__/jvm_server.cpython-37.pyc
beakerx_kernel_autotranslation-2.0.0.dist-info/LICENSE
beakerx_kernel_autotranslation-2.0.0.dist-info/METADATA
beakerx_kernel_autotranslation-2.0.0.dist-info/NOTICE
beakerx_kernel_autotranslation-2.0.0.dist-info/WHEEL
beakerx_kernel_autotranslation-2.0.0.dist-info/entry_points.txt
beakerx_kernel_autotranslation-2.0.0.dist-info/top_level.txt
beakerx_kernel_autotranslation-2.0.0.dist-info/RECORD
